fairpy/__init__.py
fairpy/dataset/__init__.py
fairpy/dataset/_adult.py
fairpy/dataset/_bank.py
fairpy/dataset/_base.py
fairpy/dataset/_compas.py
fairpy/dataset/_credit.py
fairpy/dataset/_dutch.py
fairpy/dataset/_german.py
fairpy/dataset/_oulad.py
fairpy/dataset/_xing.py
fairpy/metric/__init__.py
fairpy/metric/_classification.py
fairpy/metric/_ranking.py
fairpy/model/__init__.py
fairpy/model/_base.py
fairpy/model/_di_remover.py
fairpy/model/_eq_odds_calib.py
fairpy/model/_fair_cstr.py
fairpy/model/_fair_erm.py
fairpy/model/_fair_glm.py
fairpy/model/_fair_rank.py
fairpy/model/_ifair.py
fairpy/model/_label_bias.py
fairpy/utils/__init__.py
fairpy/utils/encode.py
test/__init__.py
fairpy-0.1.0.dist-info/LICENSE
fairpy-0.1.0.dist-info/METADATA
fairpy-0.1.0.dist-info/WHEEL
fairpy-0.1.0.dist-info/top_level.txt
fairpy-0.1.0.dist-info/RECORD
